breez_liquid_sdk/__init__.py
breez_liquid_sdk/breez_liquid_sdk.py
breez_liquid_sdk/breez_liquid_sdk_bindings.dll
breez_liquid_sdk/msvcp140.dll
breez_liquid_sdk/vcruntime140.dll
breez_liquid_sdk-0.1.2.dev5.dist-info/METADATA
breez_liquid_sdk-0.1.2.dev5.dist-info/WHEEL
breez_liquid_sdk-0.1.2.dev5.dist-info/top_level.txt
breez_liquid_sdk-0.1.2.dev5.dist-info/RECORD
