Metadata-Version: 2.1
Name: breez_liquid_sdk
Version: 0.1.2.dev5
Summary: Python language bindings for the Breez Liquid SDK
Home-page: https://github.com/breez/breez-liquid-sdk
Author: Breez <contact@breez.technology>
License: MIT
